retsdk/__init__.py
retsdk/client.py
retsdk/exceptions.py
retsdk/utilities.py
tests/__init__.py
tests/test_client_setup.py
tests/test_response_handling.py
tests/test_type_casting.py
retsdk-1.0.2.dist-info/LICENSE
retsdk-1.0.2.dist-info/METADATA
retsdk-1.0.2.dist-info/WHEEL
retsdk-1.0.2.dist-info/top_level.txt
retsdk-1.0.2.dist-info/RECORD
