Metadata-Version: 2.1
Name: retsdk
Version: 1.0.2
Summary: Python SDK for the real estate transaction standard (RETS)
Home-page: https://github.com/5150brien/retsdk
Author: D O'Brien
Author-email: dobrien@my.ccsu.edu
License: MIT
Keywords: rets real estate
Platform: UNKNOWN
Classifier: Programming Language :: Python :: 3
Classifier: License :: OSI Approved :: MIT License
Classifier: Operating System :: OS Independent
Requires-Python: >=3
